siu_data/__init__.py
siu_data/portal_data.py
siu_data/portal_de_transparencia.py
siu_data/query_file.py
siu_data/queries/1-PRESUPUESTO-tablero_01.json
siu_data/queries/1-PRESUPUESTO-tablero_02.json
siu_data/queries/1-PRESUPUESTO-tablero_03.json
siu_data/queries/1-PRESUPUESTO-tablero_04.json
siu_data/queries/1-PRESUPUESTO-tablero_05.json
siu_data/queries/2-COMPRAS-tablero_06.json
siu_data/queries/2-COMPRAS-tablero_07.json
siu_data/queries/2-COMPRAS-tablero_08.json
siu_data/queries/2-COMPRAS-tablero_09.json
siu_data/queries/2-COMPRAS-tablero_10.json
siu_data/queries/3-PATRIMONIO-tablero_11.json
siu_data/queries/3-PATRIMONIO-tablero_12.json
siu_data/queries/3-PATRIMONIO-tablero_13.json
siu_data/queries/3-PATRIMONIO-tablero_14.json
siu_data/queries/3-PATRIMONIO-tablero_15.json
siu_data/queries/4-RRHH-tablero_16.json
siu_data/queries/4-RRHH-tablero_17.json
siu_data/queries/4-RRHH-tablero_18.json
siu_data/queries/4-RRHH-tablero_19.json
siu_data/queries/4-RRHH-tablero_20.json
siu_data/queries/5-ACADEMICA-tablero_21.json
siu_data/queries/5-ACADEMICA-tablero_22.json
siu_data/queries/5-ACADEMICA-tablero_23.json
siu_data/queries/5-ACADEMICA-tablero_24.json
siu_data/queries/5-ACADEMICA-tablero_25.json
siu_data/queries/5-ACADEMICA-tablero_26.json
siu_data-0.3.6.dist-info/LICENSE
siu_data-0.3.6.dist-info/METADATA
siu_data-0.3.6.dist-info/WHEEL
siu_data-0.3.6.dist-info/top_level.txt
siu_data-0.3.6.dist-info/RECORD
