Metadata-Version: 2.1
Name: siu-data
Version: 0.3.6
Summary: SIU data
Home-page: https://github.com/avdata99/pySIUdata
Author: Andres Vazquez
Author-email: andres@data99.com.ar
License: MIT
Keywords: SIU
Platform: UNKNOWN
Classifier: Development Status :: 4 - Beta
Classifier: License :: OSI Approved :: MIT License
Classifier: Programming Language :: Python :: 3.6
Classifier: Programming Language :: Python :: 3.7
Classifier: Programming Language :: Python :: 3.8
Classifier: Programming Language :: Python :: 3.9
Requires-Dist: pyexcel-xls (>=0.5.8)
Requires-Dist: pyexcel-xlsx (>=0.5.8)
Requires-Dist: pyexcel (>=-0.5.15)
Requires-Dist: python-slugify (>=1.2.6)
